chompt/__init__.py
chompt/chompt.py
chompt-1.1.8.dist-info/METADATA
chompt-1.1.8.dist-info/RECORD
chompt-1.1.8.dist-info/WHEEL
chompt-1.1.8.dist-info/top_level.txt
