Metadata-Version: 2.1
Name: chompt
Version: 1.1.8
Summary: Chainable Object Methods for Python Testing
Home-page: https://github.com/tbonelaforge/chompt
Author: Terrance Ford
Author-email: ttf0809@gmail.com
License: MIT
Keywords: testing api object method chaining
Platform: UNKNOWN
Classifier: Development Status :: 3 - Alpha
Classifier: Intended Audience :: Developers
Classifier: Topic :: Software Development :: Testing
Classifier: License :: OSI Approved :: MIT License
Classifier: Programming Language :: Python :: 2
Classifier: Programming Language :: Python :: 2.7
Classifier: Programming Language :: Python :: 3
Classifier: Programming Language :: Python :: 3.3
Classifier: Programming Language :: Python :: 3.4
Classifier: Programming Language :: Python :: 3.5
